neuron_morphology/VERSION.txt
neuron_morphology/__init__.py
neuron_morphology/constants.py
neuron_morphology/lims_apical_queries.py
neuron_morphology/logging_config.ini
neuron_morphology/marker.py
neuron_morphology/morphology.py
neuron_morphology/morphology_builder.py
neuron_morphology/swc_io.py
neuron_morphology/feature_extractor/__init__.py
neuron_morphology/feature_extractor/__main__.py
neuron_morphology/feature_extractor/_schemas.py
neuron_morphology/feature_extractor/data.py
neuron_morphology/feature_extractor/feature_extraction_run.py
neuron_morphology/feature_extractor/feature_extractor.py
neuron_morphology/feature_extractor/feature_specialization.py
neuron_morphology/feature_extractor/feature_writer.py
neuron_morphology/feature_extractor/mark.py
neuron_morphology/feature_extractor/marked_feature.py
neuron_morphology/feature_extractor/run_feature_extraction.py
neuron_morphology/feature_extractor/utilities.py
neuron_morphology/features/__init__.py
neuron_morphology/features/default_features.py
neuron_morphology/features/dimension.py
neuron_morphology/features/intrinsic.py
neuron_morphology/features/path.py
neuron_morphology/features/size.py
neuron_morphology/features/soma.py
neuron_morphology/features/branching/__init__.py
neuron_morphology/features/branching/bifurcations.py
neuron_morphology/features/layer/__init__.py
neuron_morphology/features/layer/layer_histogram.py
neuron_morphology/features/layer/layered_point_depths.py
neuron_morphology/features/layer/reference_layer_depths.py
neuron_morphology/features/statistics/__init__.py
neuron_morphology/features/statistics/coordinates.py
neuron_morphology/features/statistics/moments.py
neuron_morphology/features/statistics/moments_along_max_distance_projection.py
neuron_morphology/features/statistics/overlap.py
neuron_morphology/layered_point_depths/__init__.py
neuron_morphology/layered_point_depths/__main__.py
neuron_morphology/layered_point_depths/_schemas.py
neuron_morphology/pipeline/__init__.py
neuron_morphology-1.2.1.dist-info/LICENSE
neuron_morphology-1.2.1.dist-info/METADATA
neuron_morphology-1.2.1.dist-info/WHEEL
neuron_morphology-1.2.1.dist-info/entry_points.txt
neuron_morphology-1.2.1.dist-info/top_level.txt
neuron_morphology-1.2.1.dist-info/RECORD
