Metadata-Version: 2.1
Name: neuron-morphology
Version: 1.2.1
Summary: Tools for working with single-neuron morphological reconstructions
Author: Allen Institute for Brain Science
Author-email: Marmot@AllenInstitute.onmicrosoft.com
Keywords: neuroscience,bioinformatics,scientific
Classifier: Development Status :: 4 - Beta
Classifier: Intended Audience :: Science/Research
Classifier: License :: Other/Proprietary License
Classifier: Natural Language :: English
Classifier: Operating System :: OS Independent
Classifier: Programming Language :: Python :: 3.8
Classifier: Topic :: Scientific/Engineering :: Bio-Informatics
License-File: LICENSE
Requires-Dist: matplotlib
Requires-Dist: pillow
Requires-Dist: pandas
Requires-Dist: numpy >=1.14.2
Requires-Dist: scipy >=1.0.0
Requires-Dist: six
Requires-Dist: allensdk
Requires-Dist: argschema
Requires-Dist: glymur <1.0.0
Requires-Dist: shapely <2.0.0
Requires-Dist: imageio <3.0.0
Requires-Dist: pg8000 <2.0.0
Requires-Dist: boto3 >=1.12.42
Requires-Dist: cloud-files
Requires-Dist: scikit-image >0.17
Requires-Dist: tables >=3.8
Provides-Extra: streamlines
Requires-Dist: fenics-dolfinx ; extra == 'streamlines'
Requires-Dist: python-gmsh ; extra == 'streamlines'
Requires-Dist: rasterio ; extra == 'streamlines'
